bad_engine/__init__.py
bad_engine/button.py
bad_engine/game_object.py
bad_engine/scene.py
bad_engine/vector.py
bad_game_engine-1.0.2.dist-info/LICENSE
bad_game_engine-1.0.2.dist-info/METADATA
bad_game_engine-1.0.2.dist-info/WHEEL
bad_game_engine-1.0.2.dist-info/top_level.txt
bad_game_engine-1.0.2.dist-info/RECORD
