Metadata-Version: 2.1
Name: bad-game-engine
Version: 1.0.2
Summary: a simple game engine I made for fun
Author: PotatMuffin
Project-URL: github, https://github.com/PotatMuffin/bad-game-engine
Requires-Python: >=3.9
License-File: LICENSE
Requires-Dist: tk
